AUTHORS
COPYING
COPYING.LESSER
MANIFEST.in
README
setup.py
kmod/__init__.py
kmod/_libkmod_h.pxd
kmod/_util.pxd
kmod/_util.pyx
kmod/error.py
kmod/kmod.pxd
kmod/kmod.pyx
kmod/list.pxd
kmod/list.pyx
kmod/module.pxd
kmod/module.pyx
kmod/version.py
kmod.egg-info/PKG-INFO
kmod.egg-info/SOURCES.txt
kmod.egg-info/dependency_links.txt
kmod.egg-info/requires.txt
kmod.egg-info/top_level.txt