Metadata-Version: 1.1
Name: kmod
Version: 0.9.2
Summary: Python binding for kmod
Home-page: UNKNOWN
Author: Andy Grover
Author-email: agrover@redhat.com
License: UNKNOWN
Platform: UNKNOWN
Provides: kmod
